fastscoredeploy/Model.py
fastscoredeploy/Schema.py
fastscoredeploy/Stream.py
fastscoredeploy/__init__.py
fastscoredeploy/errors.py
fastscoredeploy/ipmagic.py
fastscoredeploy/version.py
fastscoredeploy/codec/__init__.py
fastscoredeploy/codec/_runner.py
fastscoredeploy/codec/_schemer.py
fastscoredeploy/codec/codec.py
fastscoredeploy/codec/datatype.py
fastscoredeploy/suite/Connect.py
fastscoredeploy/suite/Engine.py
fastscoredeploy/suite/Instance.py
fastscoredeploy/suite/ModelManage.py
fastscoredeploy/suite/__init__.py
test/__init__.py
test/test_codec.py
test/test_datatype.py
test/test_model.py
test/test_suite.py
fastscoredeploy-1.10.4.dist-info/METADATA
fastscoredeploy-1.10.4.dist-info/WHEEL
fastscoredeploy-1.10.4.dist-info/top_level.txt
fastscoredeploy-1.10.4.dist-info/RECORD
