Metadata-Version: 2.1
Name: fastscoredeploy
Version: 1.10.4
Summary: FastScore Deploy
Home-page: UNKNOWN
Author: Open Data Group
Author-email: support@opendatagroup.com
License: UNKNOWN
Platform: UNKNOWN
Requires-Dist: iso8601 (>=0.1.11)
Requires-Dist: PyYAML (>=3.11)
Requires-Dist: requests (>=2.11.1)
Requires-Dist: tabulate (>=0.7.5)
Requires-Dist: websocket-client (>=0.37.0)
Requires-Dist: avro-python3 (>=1.7.6)
Requires-Dist: fastavro
Requires-Dist: six
Requires-Dist: numpy (>=1.6.1)
Requires-Dist: pandas (>=0.19.0)
Requires-Dist: fastscore
